<?xml version="1.0" encoding="UTF-8"?>
<Root>
  <IRREPS_INFO>
    <QPOINT_NUMBER>3</QPOINT_NUMBER>
    <QPOINT_GROUP_RANK>8</QPOINT_GROUP_RANK>
    <MINUS_Q_SYM>true</MINUS_Q_SYM>
    <NUMBER_IRR_REP>4</NUMBER_IRR_REP>
    <REPRESENTION.1>
      <NUMBER_OF_PERTURBATIONS>1</NUMBER_OF_PERTURBATIONS>
      <PERTURBATION.1>
        <DISPLACEMENT_PATTERN>
  0.000000000000000E+000  0.000000000000000E+000
  0.000000000000000E+000  0.000000000000000E+000
  0.000000000000000E+000  0.000000000000000E+000
  4.684433448476618E-017  0.000000000000000E+000
  -1.00000000000000       0.000000000000000E+000
  6.541683398558340E-017  0.000000000000000E+000
        </DISPLACEMENT_PATTERN>
      </PERTURBATION.1>
    </REPRESENTION.1>
    <REPRESENTION.2>
      <NUMBER_OF_PERTURBATIONS>1</NUMBER_OF_PERTURBATIONS>
      <PERTURBATION.1>
        <DISPLACEMENT_PATTERN>
  2.457575667864938E-016  0.000000000000000E+000
  -1.00000000000000       0.000000000000000E+000
 -3.739460285286646E-016  0.000000000000000E+000
  0.000000000000000E+000  0.000000000000000E+000
  0.000000000000000E+000  0.000000000000000E+000
  0.000000000000000E+000  0.000000000000000E+000
        </DISPLACEMENT_PATTERN>
      </PERTURBATION.1>
    </REPRESENTION.2>
    <REPRESENTION.3>
      <NUMBER_OF_PERTURBATIONS>2</NUMBER_OF_PERTURBATIONS>
      <PERTURBATION.1>
        <DISPLACEMENT_PATTERN>
  0.000000000000000E+000  0.000000000000000E+000
  0.000000000000000E+000  0.000000000000000E+000
  0.000000000000000E+000  0.000000000000000E+000
 -0.792988855709944       0.000000000000000E+000
  9.164201788655050E-018  0.000000000000000E+000
  0.609236140359249       0.000000000000000E+000
        </DISPLACEMENT_PATTERN>
      </PERTURBATION.1>
      <PERTURBATION.2>
        <DISPLACEMENT_PATTERN>
  0.000000000000000E+000  0.000000000000000E+000
  0.000000000000000E+000  0.000000000000000E+000
  0.000000000000000E+000  0.000000000000000E+000
 -0.609236140359248       0.000000000000000E+000
 -7.545335678749512E-017  0.000000000000000E+000
 -0.792988855709944       0.000000000000000E+000
        </DISPLACEMENT_PATTERN>
      </PERTURBATION.2>
    </REPRESENTION.3>
    <REPRESENTION.4>
      <NUMBER_OF_PERTURBATIONS>2</NUMBER_OF_PERTURBATIONS>
      <PERTURBATION.1>
        <DISPLACEMENT_PATTERN>
 -0.229039333725547       0.000000000000000E+000
  2.881389567344454E-016  0.000000000000000E+000
 -0.973417168333576       0.000000000000000E+000
  0.000000000000000E+000  0.000000000000000E+000
  0.000000000000000E+000  0.000000000000000E+000
  0.000000000000000E+000  0.000000000000000E+000
        </DISPLACEMENT_PATTERN>
      </PERTURBATION.1>
      <PERTURBATION.2>
        <DISPLACEMENT_PATTERN>
 -0.973417168333576       0.000000000000000E+000
 -3.005367054637130E-016  0.000000000000000E+000
  0.229039333725547       0.000000000000000E+000
  0.000000000000000E+000  0.000000000000000E+000
  0.000000000000000E+000  0.000000000000000E+000
  0.000000000000000E+000  0.000000000000000E+000
        </DISPLACEMENT_PATTERN>
      </PERTURBATION.2>
    </REPRESENTION.4>
  </IRREPS_INFO>
</Root>
